fakexyz/__init__.py
fakexyz/data_loader.py
fakexyz/generator.py
fakexyz/iban.py
fakexyz/info_extractor.py
fakexyz/data/ad.json
fakexyz/data/ae.json
fakexyz/data/af.json
fakexyz/data/ag.json
fakexyz/data/al.json
fakexyz/data/am.json
fakexyz/data/ao.json
fakexyz/data/ar.json
fakexyz/data/as.json
fakexyz/data/at.json
fakexyz/data/au.json
fakexyz/data/az.json
fakexyz/data/ba.json
fakexyz/data/bb.json
fakexyz/data/bd.json
fakexyz/data/be.json
fakexyz/data/bf.json
fakexyz/data/bg.json
fakexyz/data/bh.json
fakexyz/data/bi.json
fakexyz/data/bj.json
fakexyz/data/bm.json
fakexyz/data/bn.json
fakexyz/data/bo.json
fakexyz/data/bq.json
fakexyz/data/br.json
fakexyz/data/bs.json
fakexyz/data/bt.json
fakexyz/data/bw.json
fakexyz/data/by.json
fakexyz/data/bz.json
fakexyz/data/ca.json
fakexyz/data/cd.json
fakexyz/data/cf.json
fakexyz/data/cg.json
fakexyz/data/ch.json
fakexyz/data/ci.json
fakexyz/data/cl.json
fakexyz/data/cm.json
fakexyz/data/cn.json
fakexyz/data/co.json
fakexyz/data/cr.json
fakexyz/data/cu.json
fakexyz/data/cv.json
fakexyz/data/cy.json
fakexyz/data/cz.json
fakexyz/data/de.json
fakexyz/data/dj.json
fakexyz/data/dk.json
fakexyz/data/dm.json
fakexyz/data/do.json
fakexyz/data/dz.json
fakexyz/data/ec.json
fakexyz/data/ee.json
fakexyz/data/eg.json
fakexyz/data/er.json
fakexyz/data/es.json
fakexyz/data/et.json
fakexyz/data/fi.json
fakexyz/data/fj.json
fakexyz/data/fr.json
fakexyz/data/ga.json
fakexyz/data/gd.json
fakexyz/data/ge.json
fakexyz/data/gh.json
fakexyz/data/gl.json
fakexyz/data/gr.json
fakexyz/data/gt.json
fakexyz/data/hk.json
fakexyz/data/hr.json
fakexyz/data/hu.json
fakexyz/data/id.json
fakexyz/data/ie.json
fakexyz/data/il.json
fakexyz/data/in.json
fakexyz/data/iq.json
fakexyz/data/ir.json
fakexyz/data/is.json
fakexyz/data/it.json
fakexyz/data/jo.json
fakexyz/data/jp.json
fakexyz/data/ke.json
fakexyz/data/kh.json
fakexyz/data/kr.json
fakexyz/data/kz.json
fakexyz/data/lb.json
fakexyz/data/lk.json
fakexyz/data/lt.json
fakexyz/data/lv.json
fakexyz/data/ma.json
fakexyz-2.4.dist-info/licenses/LICENSE.txt
fakexyz-2.4.dist-info/METADATA
fakexyz-2.4.dist-info/WHEEL
fakexyz-2.4.dist-info/top_level.txt
fakexyz-2.4.dist-info/RECORD
