Metadata-Version: 2.4
Name: fakexyz
Version: 2.4
Summary: Generate fake user and address information for various countries.
Home-page: https://github.com/bbinl/fakexyz.git
Author-email: Mahir Labib <islamraisul796@gmail.com>
License: MIT
Project-URL: Homepage, https://github.com/bbinl/fakexyz.git
Requires-Python: >=3.7
License-File: LICENSE.txt
Requires-Dist: fuzzywuzzy
Requires-Dist: python-Levenshtein
Requires-Dist: schwifty
Dynamic: home-page
Dynamic: license-file
Dynamic: requires-python
